{
  "AUTH": {
    "LOGIN_PAGE": {
      "BREADCRUMB": {
        "TITLE": {
          "DASHBOARD": "AUTH.LOGIN_PAGE.BREADCRUMB.TITLE.DASHBOARD"
        }
      },
      "WELCOME_TITLE": "AUTH.LOGIN_PAGE.WELCOME_TITLE",
      "LOGIN_BOX": {
        "TITLE": "AUTH.LOGIN_PAGE.LOGIN_BOX.TITLE",
        "INPUTS": {
          "USERNAME_PLACEHOLDER": "AUTH.LOGIN_PAGE.LOGIN_BOX.INPUTS.USERNAME_PLACEHOLDER",
          "PASSWORD_PLACEHOLDER": "AUTH.LOGIN_PAGE.LOGIN_BOX.INPUTS.PASSWORD_PLACEHOLDER",
          "PASSWORD_EYE_TOOLTIP": "AUTH.LOGIN_PAGE.LOGIN_BOX.INPUTS.PASSWORD_EYE_TOOLTIP"
        },
        "LOGIN_BUTTON_TEXT": "AUTH.LOGIN_PAGE.LOGIN_BOX.LOGIN_BUTTON_TEXT",
        "FORGOTTEN_PASSWORD_LINK": "AUTH.LOGIN_PAGE.LOGIN_BOX.FORGOTTEN_PASSWORD_LINK",
        "REGISTRATION_BOX": {
          "DESCRIPTION": "AUTH.LOGIN_PAGE.LOGIN_BOX.REGISTRATION_BOX.DESCRIPTION",
          "REGISTRATION_BUTTON_TEXT": "AUTH.LOGIN_PAGE.LOGIN_BOX.REGISTRATION_BOX.REGISTRATION_BUTTON_TEXT"
        }
      },
      "SYSTEM_NOTIFICATIONS": {
        "WRONG_USERNAME_OR_PASSWORD": "AUTH.LOGIN_PAGE.SYSTEM_NOTIFICATIONS.WRONG_USERNAME_OR_PASSWORD",
        "UNSUCCESSFUL_SUBSCRIPTION_DATE_QUERY": "AUTH.LOGIN_PAGE.SYSTEM_NOTIFICATIONS.UNSUCCESSFUL_SUBSCRIPTION_DATE_QUERY",
        "EXPIRATION_WARNING": "AUTH.LOGIN_PAGE.SYSTEM_NOTIFICATIONS.EXPIRATION_WARNING"
      }
    },
    "REGISTRATION_PAGE": {
      "BREADCRUMB": "AUTH.REGISTRATION_PAGE.BREADCRUMB",
      "WELCOME_TITLE": "AUTH.REGISTRATION_PAGE.WELCOME_TITLE",
      "INFO_PARAGRAPH_1": "AUTH.REGISTRATION_PAGE.INFO_PARAGRAPH_1",
      "INFO_PARAGRAPH_2": "AUTH.REGISTRATION_PAGE.INFO_PARAGRAPH_2",
      "INFO_PARAGRAPH_3": "AUTH.REGISTRATION_PAGE.INFO_PARAGRAPH_3",
      "HIGHLIGHTED_GUARANTEE": "AUTH.REGISTRATION_PAGE.HIGHLIGHTED_GUARANTEE",
      "ROLE_SELECTION": {
        "TITLE": "AUTH.REGISTRATION_PAGE.ROLE_SELECTION.TITLE",
        "DESCRIPTION": "AUTH.REGISTRATION_PAGE.ROLE_SELECTION.DESCRIPTION",
        "OPTIONS": {
          "PATIENT": "AUTH.REGISTRATION_PAGE.ROLE_SELECTION.OPTIONS.PATIENT",
          "EMPLOYEE": "AUTH.REGISTRATION_PAGE.ROLE_SELECTION.OPTIONS.EMPLOYEE",
          "ADMIN": "AUTH.REGISTRATION_PAGE.ROLE_SELECTION.OPTIONS.ADMIN"
        },
        "TABS": {
          "TITLE": "AUTH.REGISTRATION_PAGE.ROLE_SELECTION.TABS.TITLE",
          "REGISTRATION_AS_PATIENT": {
            "ROW_1": "AUTH.REGISTRATION_PAGE.ROLE_SELECTION.TABS.REGISTRATION_AS_PATIENT.ROW_1",
            "ROW_2": "AUTH.REGISTRATION_PAGE.ROLE_SELECTION.TABS.REGISTRATION_AS_PATIENT.ROW_2",
            "ROW_3": "AUTH.REGISTRATION_PAGE.ROLE_SELECTION.TABS.REGISTRATION_AS_PATIENT.ROW_3"
          },
          "REGISTRATION_AS_EMPLOYEE": {
            "ROW_1": "AUTH.REGISTRATION_PAGE.ROLE_SELECTION.TABS.REGISTRATION_AS_EMPLOYEE.ROW_1",
            "ROW_2": "AUTH.REGISTRATION_PAGE.ROLE_SELECTION.TABS.REGISTRATION_AS_EMPLOYEE.ROW_2"
          },
          "REGISTRATION_AS_ADMIN": {
            "INFORMATION_1_FIRST_PART": "AUTH.REGISTRATION_PAGE.ROLE_SELECTION.TABS.REGISTRATION_AS_ADMIN.INFORMATION_1_FIRST_PART",
            "INFORMATION_1_LINK_TEXT": "AUTH.REGISTRATION_PAGE.ROLE_SELECTION.TABS.REGISTRATION_AS_ADMIN.INFORMATION_1_LINK_TEXT",
            "INFORMATION_1_SECOND_PART": "AUTH.REGISTRATION_PAGE.ROLE_SELECTION.TABS.REGISTRATION_AS_ADMIN.INFORMATION_1_SECOND_PART",
            "INFORMATION_2": "AUTH.REGISTRATION_PAGE.ROLE_SELECTION.TABS.REGISTRATION_AS_ADMIN.INFORMATION_2",
            "FIELDS": {
              "LAST_NAME": "AUTH.REGISTRATION_PAGE.ROLE_SELECTION.TABS.REGISTRATION_AS_ADMIN.FIELDS.LAST_NAME",
              "FIRST_NAME": "AUTH.REGISTRATION_PAGE.ROLE_SELECTION.TABS.REGISTRATION_AS_ADMIN.FIELDS.FIRST_NAME",
              "EMAIL_ADDRESS": "AUTH.REGISTRATION_PAGE.ROLE_SELECTION.TABS.REGISTRATION_AS_ADMIN.FIELDS.EMAIL_ADDRESS",
              "MOBILE_NUMBER": "AUTH.REGISTRATION_PAGE.ROLE_SELECTION.TABS.REGISTRATION_AS_ADMIN.FIELDS.MOBILE_NUMBER",
              "CLINIC_NAME": "AUTH.REGISTRATION_PAGE.ROLE_SELECTION.TABS.REGISTRATION_AS_ADMIN.FIELDS.CLINIC_NAME",
              "CLINIC_NAME_HELP_TOOLTIP": "AUTH.REGISTRATION_PAGE.ROLE_SELECTION.TABS.REGISTRATION_AS_ADMIN.FIELDS.CLINIC_NAME_HELP_TOOLTIP",
              "COUPON_CODE": "AUTH.REGISTRATION_PAGE.ROLE_SELECTION.TABS.REGISTRATION_AS_ADMIN.FIELDS.COUPON_CODE",
              "USERNAME": "AUTH.REGISTRATION_PAGE.ROLE_SELECTION.TABS.REGISTRATION_AS_ADMIN.FIELDS.USERNAME",
              "USERNAME_HELP_TOOLTIP": "AUTH.REGISTRATION_PAGE.ROLE_SELECTION.TABS.REGISTRATION_AS_ADMIN.FIELDS.USERNAME_HELP_TOOLTIP",
              "PASSWORD": "AUTH.REGISTRATION_PAGE.ROLE_SELECTION.TABS.REGISTRATION_AS_ADMIN.FIELDS.PASSWORD",
              "PASSWORD_EYE_TOOLTIP": "AUTH.REGISTRATION_PAGE.ROLE_SELECTION.TABS.REGISTRATION_AS_ADMIN.FIELDS.PASSWORD_EYE_TOOLTIP",
              "PASSWORD_HELP_TOOLTIP": "AUTH.REGISTRATION_PAGE.ROLE_SELECTION.TABS.REGISTRATION_AS_ADMIN.FIELDS.PASSWORD_HELP_TOOLTIP",
              "PASSWORD_AGAIN": "AUTH.REGISTRATION_PAGE.ROLE_SELECTION.TABS.REGISTRATION_AS_ADMIN.FIELDS.PASSWORD_AGAIN",
              "PASSWORD_AGAIN_EYE_TOOLTIP": "AUTH.REGISTRATION_PAGE.ROLE_SELECTION.TABS.REGISTRATION_AS_ADMIN.FIELDS.PASSWORD_AGAIN_EYE_TOOLTIP",
              "PASSWORD_AGAIN_HELP_TOOLTIP": "AUTH.REGISTRATION_PAGE.ROLE_SELECTION.TABS.REGISTRATION_AS_ADMIN.FIELDS.PASSWORD_AGAIN_HELP_TOOLTIP"
            },
            "ACCEPT_TERMS_AND_CONDITIONS": {
              "TEXT": "AUTH.REGISTRATION_PAGE.ROLE_SELECTION.TABS.REGISTRATION_AS_ADMIN.ACCEPT_TERMS_AND_CONDITIONS.TEXT",
              "LINK_TEXT": "AUTH.REGISTRATION_PAGE.ROLE_SELECTION.TABS.REGISTRATION_AS_ADMIN.ACCEPT_TERMS_AND_CONDITIONS.LINK_TEXT"
            },
            "REGISTER_BUTTON_TEXT": "AUTH.REGISTRATION_PAGE.ROLE_SELECTION.TABS.REGISTRATION_AS_ADMIN.REGISTER_BUTTON_TEXT"
          }
        }
      },
      "SYSTEM_NOTIFICATIONS": {
        "REGISTRATION_SUCCESS": "AUTH.REGISTRATION_PAGE.SYSTEM_NOTIFICATIONS.REGISTRATION_SUCCESS"
      }
    }
  }
}
